<?xml version="1.0" encoding="UTF-8"?>
<!DOCTYPE suite SYSTEM "http://testng.org/testng-1.0.dtd">
<suite thread-count="2" parallel="methods" name="Surefire suite">
    <test name="Surefire test">
        <classes>
            <class name="localhost.surefiretestngordering.TestClass1"/>
            <class name="localhost.surefiretestngordering.TestClass2"/>
            <class name="localhost.surefiretestngordering.TestClass3"/>
            <class name="localhost.surefiretestngordering.TestClass4"/>
        </classes>
    </test> <!-- Surefire test -->
</suite> <!-- Surefire suite -->
